bffuck/__init__.py
bffuck/bffuck.py
BFFuck-3.0.0.dist-info/METADATA
BFFuck-3.0.0.dist-info/WHEEL
BFFuck-3.0.0.dist-info/entry_points.txt
BFFuck-3.0.0.dist-info/top_level.txt
BFFuck-3.0.0.dist-info/RECORD
