Metadata-Version: 2.1
Name: BFFuck
Version: 3.0.0
Summary: Makes Brainfucking Easier!
Home-page: https://github.com/none-None1/BFFuck
Classifier: Operating System :: OS Independent
Classifier: Programming Language :: Python :: 3 :: Only
Classifier: Topic :: Software Development :: Code Generators
